[
  {
    "month": 1,
    "day": 1,
    "question": "새해 첫날, 새로운 시작에 대해 어떤 다짐을 했나요?"
  },
  {
    "month": 1,
    "day": 2,
    "question": "오늘 하루 중 가장 기분 좋았던 순간은 언제였나요?"
  },
  {
    "month": 1,
    "day": 3,
    "question": "오늘 당신을 가장 크게 웃게 한 일은 무엇인가요?"
  },
  {
    "month": 1,
    "day": 4,
    "question": "오늘 느낀 감정 중 가장 강렬했던 것은 무엇인가요?"
  },
  {
    "month": 1,
    "day": 5,
    "question": "오늘 하루를 한 문장으로 표현한다면?"
  },
  {
    "month": 1,
    "day": 6,
    "question": "오늘 어떤 새로운 배움을 얻었나요?"
  },
  {
    "month": 1,
    "day": 7,
    "question": "오늘 당신을 가장 감사하게 만든 순간은 무엇인가요?"
  },
  {
    "month": 1,
    "day": 8,
    "question": "오늘 이루고자 했던 목표는 무엇이었나요?"
  },
  {
    "month": 1,
    "day": 9,
    "question": "오늘 도전한 일이 있다면 무엇인가요?"
  },
  {
    "month": 1,
    "day": 10,
    "question": "어린 시절 가장 기억에 남는 행복한 순간은 무엇인가요?"
  },
  {
    "month": 1,
    "day": 11,
    "question": "오늘 자랑스러웠던 일은 무엇인가요?"
  },
  {
    "month": 1,
    "day": 12,
    "question": "오늘 당신의 기분을 색으로 표현한다면 어떤 색인가요?"
  },
  {
    "month": 1,
    "day": 13,
    "question": "오늘 내린 결정 중 가장 중요한 것은 무엇인가요?"
  },
  {
    "month": 1,
    "day": 14,
    "question": "오늘 감사했던 사람은 누구인가요?"
  },
  {
    "month": 1,
    "day": 15,
    "question": "오늘 배우게 된 중요한 교훈은 무엇인가요?"
  },
  {
    "month": 1,
    "day": 16,
    "question": "오늘 하루를 점수로 매긴다면 몇 점인가요?"
  },
  {
    "month": 1,
    "day": 17,
    "question": "오늘 당신의 하루를 노래 제목으로 표현한다면?"
  },
  {
    "month": 1,
    "day": 18,
    "question": "오늘 가장 집중했던 일은 무엇인가요?"
  },
  {
    "month": 1,
    "day": 19,
    "question": "오늘 식사 중 가장 기억에 남는 것은 무엇인가요?"
  },
  {
    "month": 1,
    "day": 20,
    "question": "오늘 만난 사람 중 가장 인상 깊었던 사람은 누구인가요?"
  },
  {
    "month": 1,
    "day": 21,
    "question": "오늘 기뻤던 일 한 가지를 공유해 보세요."
  },
  {
    "month": 1,
    "day": 22,
    "question": "오늘 발견한 작은 행복은 무엇인가요?"
  },
  {
    "month": 1,
    "day": 23,
    "question": "오늘 위로받았던 순간이 있다면?"
  },
  {
    "month": 1,
    "day": 24,
    "question": "오늘 하루 중 가장 평화로웠던 순간은?"
  },
  {
    "month": 1,
    "day": 25,
    "question": "오늘 가장 도전적이었던 일은 무엇인가요?"
  },
  {
    "month": 1,
    "day": 26,
    "question": "오늘 느낀 감사함은 무엇인가요?"
  },
  {
    "month": 1,
    "day": 27,
    "question": "오늘 개선하고 싶은 점이 있다면 무엇인가요?"
  },
  {
    "month": 1,
    "day": 28,
    "question": "오늘 하루 중 가장 고요했던 순간은 언제였나요?"
  },
  {
    "month": 1,
    "day": 29,
    "question": "오늘 당신을 행복하게 만든 작은 일은?"
  },
  {
    "month": 1,
    "day": 30,
    "question": "오늘 되돌리고 싶은 순간이 있다면?"
  },
  {
    "month": 1,
    "day": 31,
    "question": "이번 달 가장 기억에 남는 일은 무엇인가요?"
  },
  {
    "month": 2,
    "day": 1,
    "question": "오늘 하루 가장 특별했던 순간은 무엇인가요?"
  },
  {
    "month": 2,
    "day": 2,
    "question": "오늘 나에게 가장 중요한 가치는 무엇이었나요?"
  },
  {
    "month": 2,
    "day": 3,
    "question": "최근에 나를 행복하게 만든 일은 무엇인가요?"
  },
  {
    "month": 2,
    "day": 4,
    "question": "오늘 하루를 한 문장으로 표현한다면?"
  },
  {
    "month": 2,
    "day": 5,
    "question": "지금 가장 감사한 것은 무엇인가요?"
  },
  {
    "month": 2,
    "day": 6,
    "question": "오늘 어떤 배움을 얻었나요?"
  },
  {
    "month": 2,
    "day": 7,
    "question": "오늘 나를 웃게 만든 일은 무엇인가요?"
  },
  {
    "month": 2,
    "day": 8,
    "question": "오늘 느낀 가장 강렬한 감정은 무엇인가요?"
  },
  {
    "month": 2,
    "day": 9,
    "question": "오늘 새롭게 시도한 일이 있다면 무엇인가요?"
  },
  {
    "month": 2,
    "day": 10,
    "question": "어린 시절 가장 좋아했던 일은 무엇인가요?"
  },
  {
    "month": 2,
    "day": 11,
    "question": "오늘 나를 자랑스럽게 만든 일은 무엇인가요?"
  },
  {
    "month": 2,
    "day": 12,
    "question": "오늘의 날씨와 나의 기분은 어땠나요?"
  },
  {
    "month": 2,
    "day": 13,
    "question": "오늘 내가 내린 가장 좋은 결정은 무엇인가요?"
  },
  {
    "month": 2,
    "day": 14,
    "question": "오늘 감사한 사람은 누구인가요?"
  },
  {
    "month": 2,
    "day": 15,
    "question": "오늘 내가 배운 가장 중요한 교훈은 무엇인가요?"
  },
  {
    "month": 2,
    "day": 16,
    "question": "오늘 하루를 점수로 매긴다면 몇 점인가요?"
  },
  {
    "month": 2,
    "day": 17,
    "question": "오늘 나의 기분을 색으로 표현한다면?"
  },
  {
    "month": 2,
    "day": 18,
    "question": "오늘 이루고 싶은 목표는 무엇이었나요?"
  },
  {
    "month": 2,
    "day": 19,
    "question": "오늘의 식사 중 가장 맛있었던 것은 무엇인가요?"
  },
  {
    "month": 2,
    "day": 20,
    "question": "오늘 내가 만난 사람 중 가장 인상 깊었던 사람은 누구인가요?"
  },
  {
    "month": 2,
    "day": 21,
    "question": "오늘의 하루를 노래 제목으로 표현한다면?"
  },
  {
    "month": 2,
    "day": 22,
    "question": "오늘 내가 해낸 일 중 가장 기뻤던 것은?"
  },
  {
    "month": 2,
    "day": 23,
    "question": "오늘 나에게 위로가 되었던 순간은?"
  },
  {
    "month": 2,
    "day": 24,
    "question": "오늘 발견한 작은 행복은 무엇인가요?"
  },
  {
    "month": 2,
    "day": 25,
    "question": "오늘 하루 중 가장 도전적인 순간은 무엇이었나요?"
  },
  {
    "month": 2,
    "day": 26,
    "question": "오늘 나의 일상에서 감사한 점은 무엇인가요?"
  },
  {
    "month": 2,
    "day": 27,
    "question": "오늘 내가 개선할 수 있는 점은 무엇인가요?"
  },
  {
    "month": 2,
    "day": 28,
    "question": "오늘 하루 중 가장 평화로웠던 순간은 언제였나요?"
  },
  {
    "month": 3,
    "day": 1,
    "question": "오늘 하루 가장 특별했던 순간은 무엇인가요?"
  },
  {
    "month": 3,
    "day": 2,
    "question": "오늘 나에게 가장 중요한 가치는 무엇이었나요?"
  },
  {
    "month": 3,
    "day": 3,
    "question": "최근에 나를 행복하게 만든 일은 무엇인가요?"
  },
  {
    "month": 3,
    "day": 4,
    "question": "오늘 하루를 한 문장으로 표현한다면?"
  },
  {
    "month": 3,
    "day": 5,
    "question": "지금 가장 감사한 것은 무엇인가요?"
  },
  {
    "month": 3,
    "day": 6,
    "question": "오늘 어떤 배움을 얻었나요?"
  },
  {
    "month": 3,
    "day": 7,
    "question": "오늘 나를 웃게 만든 일은 무엇인가요?"
  },
  {
    "month": 3,
    "day": 8,
    "question": "오늘 느낀 가장 강렬한 감정은 무엇인가요?"
  },
  {
    "month": 3,
    "day": 9,
    "question": "오늘 새롭게 시도한 일이 있다면 무엇인가요?"
  },
  {
    "month": 3,
    "day": 10,
    "question": "어린 시절 가장 좋아했던 일은 무엇인가요?"
  },
  {
    "month": 3,
    "day": 11,
    "question": "오늘 나를 자랑스럽게 만든 일은 무엇인가요?"
  },
  {
    "month": 3,
    "day": 12,
    "question": "오늘의 날씨와 나의 기분은 어땠나요?"
  },
  {
    "month": 3,
    "day": 13,
    "question": "오늘 내가 내린 가장 좋은 결정은 무엇인가요?"
  },
  {
    "month": 3,
    "day": 14,
    "question": "오늘 감사한 사람은 누구인가요?"
  },
  {
    "month": 3,
    "day": 15,
    "question": "오늘 내가 배운 가장 중요한 교훈은 무엇인가요?"
  },
  {
    "month": 3,
    "day": 16,
    "question": "오늘 하루를 점수로 매긴다면 몇 점인가요?"
  },
  {
    "month": 3,
    "day": 17,
    "question": "오늘 나의 기분을 색으로 표현한다면?"
  },
  {
    "month": 3,
    "day": 18,
    "question": "오늘 이루고 싶은 목표는 무엇이었나요?"
  },
  {
    "month": 3,
    "day": 19,
    "question": "오늘의 식사 중 가장 맛있었던 것은 무엇인가요?"
  },
  {
    "month": 3,
    "day": 20,
    "question": "오늘 내가 만난 사람 중 가장 인상 깊었던 사람은 누구인가요?"
  },
  {
    "month": 3,
    "day": 21,
    "question": "오늘의 하루를 노래 제목으로 표현한다면?"
  },
  {
    "month": 3,
    "day": 22,
    "question": "오늘 내가 해낸 일 중 가장 기뻤던 것은?"
  },
  {
    "month": 3,
    "day": 23,
    "question": "오늘 나에게 위로가 되었던 순간은?"
  },
  {
    "month": 3,
    "day": 24,
    "question": "오늘 발견한 작은 행복은 무엇인가요?"
  },
  {
    "month": 3,
    "day": 25,
    "question": "오늘 하루 중 가장 도전적인 순간은 무엇이었나요?"
  },
  {
    "month": 3,
    "day": 26,
    "question": "오늘 나의 일상에서 감사한 점은 무엇인가요?"
  },
  {
    "month": 3,
    "day": 27,
    "question": "오늘 내가 개선할 수 있는 점은 무엇인가요?"
  },
  {
    "month": 3,
    "day": 28,
    "question": "오늘 하루 중 가장 평화로웠던 순간은 언제였나요?"
  },
  {
    "month": 3,
    "day": 29,
    "question": "오늘 나를 행복하게 한 작은 일은 무엇인가요?"
  },
  {
    "month": 3,
    "day": 30,
    "question": "오늘 만약 되돌릴 수 있다면 무엇을 바꾸고 싶나요?"
  },
  {
    "month": 3,
    "day": 31,
    "question": "이번 달 가장 기억에 남는 일은 무엇인가요?"
  },
  {
    "month": 4,
    "day": 1,
    "question": "오늘 하루 가장 특별했던 순간은 무엇인가요?"
  },
  {
    "month": 4,
    "day": 2,
    "question": "오늘 나에게 가장 중요한 가치는 무엇이었나요?"
  },
  {
    "month": 4,
    "day": 3,
    "question": "최근에 나를 행복하게 만든 일은 무엇인가요?"
  },
  {
    "month": 4,
    "day": 4,
    "question": "오늘 하루를 한 문장으로 표현한다면?"
  },
  {
    "month": 4,
    "day": 5,
    "question": "지금 가장 감사한 것은 무엇인가요?"
  },
  {
    "month": 4,
    "day": 6,
    "question": "오늘 어떤 배움을 얻었나요?"
  },
  {
    "month": 4,
    "day": 7,
    "question": "오늘 나를 웃게 만든 일은 무엇인가요?"
  },
  {
    "month": 4,
    "day": 8,
    "question": "오늘 느낀 가장 강렬한 감정은 무엇인가요?"
  },
  {
    "month": 4,
    "day": 9,
    "question": "오늘 새롭게 시도한 일이 있다면 무엇인가요?"
  },
  {
    "month": 4,
    "day": 10,
    "question": "어린 시절 가장 좋아했던 일은 무엇인가요?"
  },
  {
    "month": 4,
    "day": 11,
    "question": "오늘 나를 자랑스럽게 만든 일은 무엇인가요?"
  },
  {
    "month": 4,
    "day": 12,
    "question": "오늘의 날씨와 나의 기분은 어땠나요?"
  },
  {
    "month": 4,
    "day": 13,
    "question": "오늘 내가 내린 가장 좋은 결정은 무엇인가요?"
  },
  {
    "month": 4,
    "day": 14,
    "question": "오늘 감사한 사람은 누구인가요?"
  },
  {
    "month": 4,
    "day": 15,
    "question": "오늘 내가 배운 가장 중요한 교훈은 무엇인가요?"
  },
  {
    "month": 4,
    "day": 16,
    "question": "오늘 하루를 점수로 매긴다면 몇 점인가요?"
  },
  {
    "month": 4,
    "day": 17,
    "question": "오늘 나의 기분을 색으로 표현한다면?"
  },
  {
    "month": 4,
    "day": 18,
    "question": "오늘 이루고 싶은 목표는 무엇이었나요?"
  },
  {
    "month": 4,
    "day": 19,
    "question": "오늘의 식사 중 가장 맛있었던 것은 무엇인가요?"
  },
  {
    "month": 4,
    "day": 20,
    "question": "오늘 내가 만난 사람 중 가장 인상 깊었던 사람은 누구인가요?"
  },
  {
    "month": 4,
    "day": 21,
    "question": "오늘의 하루를 노래 제목으로 표현한다면?"
  },
  {
    "month": 4,
    "day": 22,
    "question": "오늘 내가 해낸 일 중 가장 기뻤던 것은?"
  },
  {
    "month": 4,
    "day": 23,
    "question": "오늘 나에게 위로가 되었던 순간은?"
  },
  {
    "month": 4,
    "day": 24,
    "question": "오늘 발견한 작은 행복은 무엇인가요?"
  },
  {
    "month": 4,
    "day": 25,
    "question": "오늘 하루 중 가장 도전적인 순간은 무엇이었나요?"
  },
  {
    "month": 4,
    "day": 26,
    "question": "오늘 나의 일상에서 감사한 점은 무엇인가요?"
  },
  {
    "month": 4,
    "day": 27,
    "question": "오늘 내가 개선할 수 있는 점은 무엇인가요?"
  },
  {
    "month": 4,
    "day": 28,
    "question": "오늘 하루 중 가장 평화로웠던 순간은 언제였나요?"
  },
  {
    "month": 4,
    "day": 29,
    "question": "오늘 나를 행복하게 한 작은 일은 무엇인가요?"
  },
  {
    "month": 4,
    "day": 30,
    "question": "오늘 만약 되돌릴 수 있다면 무엇을 바꾸고 싶나요?"
  },
  {
    "month": 5,
    "day": 1,
    "question": "오늘 하루 가장 특별했던 순간은 무엇인가요?"
  },
  {
    "month": 5,
    "day": 2,
    "question": "오늘 나에게 가장 중요한 가치는 무엇이었나요?"
  },
  {
    "month": 5,
    "day": 3,
    "question": "최근에 나를 행복하게 만든 일은 무엇인가요?"
  },
  {
    "month": 5,
    "day": 4,
    "question": "오늘 하루를 한 문장으로 표현한다면?"
  },
  {
    "month": 5,
    "day": 5,
    "question": "지금 가장 감사한 것은 무엇인가요?"
  },
  {
    "month": 5,
    "day": 6,
    "question": "오늘 어떤 배움을 얻었나요?"
  },
  {
    "month": 5,
    "day": 7,
    "question": "오늘 나를 웃게 만든 일은 무엇인가요?"
  },
  {
    "month": 5,
    "day": 8,
    "question": "오늘 느낀 가장 강렬한 감정은 무엇인가요?"
  },
  {
    "month": 5,
    "day": 9,
    "question": "오늘 새롭게 시도한 일이 있다면 무엇인가요?"
  },
  {
    "month": 5,
    "day": 10,
    "question": "어린 시절 가장 좋아했던 일은 무엇인가요?"
  },
  {
    "month": 5,
    "day": 11,
    "question": "오늘 나를 자랑스럽게 만든 일은 무엇인가요?"
  },
  {
    "month": 5,
    "day": 12,
    "question": "오늘의 날씨와 나의 기분은 어땠나요?"
  },
  {
    "month": 5,
    "day": 13,
    "question": "오늘 내가 내린 가장 좋은 결정은 무엇인가요?"
  },
  {
    "month": 5,
    "day": 14,
    "question": "오늘 감사한 사람은 누구인가요?"
  },
  {
    "month": 5,
    "day": 15,
    "question": "오늘 내가 배운 가장 중요한 교훈은 무엇인가요?"
  },
  {
    "month": 5,
    "day": 16,
    "question": "오늘 하루를 점수로 매긴다면 몇 점인가요?"
  },
  {
    "month": 5,
    "day": 17,
    "question": "오늘 나의 기분을 색으로 표현한다면?"
  },
  {
    "month": 5,
    "day": 18,
    "question": "오늘 이루고 싶은 목표는 무엇이었나요?"
  },
  {
    "month": 5,
    "day": 19,
    "question": "오늘의 식사 중 가장 맛있었던 것은 무엇인가요?"
  },
  {
    "month": 5,
    "day": 20,
    "question": "오늘 내가 만난 사람 중 가장 인상 깊었던 사람은 누구인가요?"
  },
  {
    "month": 5,
    "day": 21,
    "question": "오늘의 하루를 노래 제목으로 표현한다면?"
  },
  {
    "month": 5,
    "day": 22,
    "question": "오늘 내가 해낸 일 중 가장 기뻤던 것은?"
  },
  {
    "month": 5,
    "day": 23,
    "question": "오늘 나에게 위로가 되었던 순간은?"
  },
  {
    "month": 5,
    "day": 24,
    "question": "오늘 발견한 작은 행복은 무엇인가요?"
  },
  {
    "month": 5,
    "day": 25,
    "question": "오늘 하루 중 가장 도전적인 순간은 무엇이었나요?"
  },
  {
    "month": 5,
    "day": 26,
    "question": "오늘 나의 일상에서 감사한 점은 무엇인가요?"
  },
  {
    "month": 5,
    "day": 27,
    "question": "오늘 내가 개선할 수 있는 점은 무엇인가요?"
  },
  {
    "month": 5,
    "day": 28,
    "question": "오늘 하루 중 가장 평화로웠던 순간은 언제였나요?"
  },
  {
    "month": 5,
    "day": 29,
    "question": "오늘 나를 행복하게 한 작은 일은 무엇인가요?"
  },
  {
    "month": 5,
    "day": 30,
    "question": "오늘 만약 되돌릴 수 있다면 무엇을 바꾸고 싶나요?"
  },
  {
    "month": 5,
    "day": 31,
    "question": "이번 달 가장 기억에 남는 일은 무엇인가요?"
  },
  {
    "month": 6,
    "day": 1,
    "question": "오늘 하루 가장 특별했던 순간은 무엇인가요?"
  },
  {
    "month": 6,
    "day": 2,
    "question": "오늘 나에게 가장 중요한 가치는 무엇이었나요?"
  },
  {
    "month": 6,
    "day": 3,
    "question": "최근에 나를 행복하게 만든 일은 무엇인가요?"
  },
  {
    "month": 6,
    "day": 4,
    "question": "오늘 하루를 한 문장으로 표현한다면?"
  },
  {
    "month": 6,
    "day": 5,
    "question": "지금 가장 감사한 것은 무엇인가요?"
  },
  {
    "month": 6,
    "day": 6,
    "question": "오늘 어떤 배움을 얻었나요?"
  },
  {
    "month": 6,
    "day": 7,
    "question": "오늘 나를 웃게 만든 일은 무엇인가요?"
  },
  {
    "month": 6,
    "day": 8,
    "question": "오늘 느낀 가장 강렬한 감정은 무엇인가요?"
  },
  {
    "month": 6,
    "day": 9,
    "question": "오늘 새롭게 시도한 일이 있다면 무엇인가요?"
  },
  {
    "month": 6,
    "day": 10,
    "question": "어린 시절 가장 좋아했던 일은 무엇인가요?"
  },
  {
    "month": 6,
    "day": 11,
    "question": "오늘 나를 자랑스럽게 만든 일은 무엇인가요?"
  },
  {
    "month": 6,
    "day": 12,
    "question": "오늘의 날씨와 나의 기분은 어땠나요?"
  },
  {
    "month": 6,
    "day": 13,
    "question": "오늘 내가 내린 가장 좋은 결정은 무엇인가요?"
  },
  {
    "month": 6,
    "day": 14,
    "question": "오늘 감사한 사람은 누구인가요?"
  },
  {
    "month": 6,
    "day": 15,
    "question": "오늘 내가 배운 가장 중요한 교훈은 무엇인가요?"
  },
  {
    "month": 6,
    "day": 16,
    "question": "오늘 하루를 점수로 매긴다면 몇 점인가요?"
  },
  {
    "month": 6,
    "day": 17,
    "question": "오늘 나의 기분을 색으로 표현한다면?"
  },
  {
    "month": 6,
    "day": 18,
    "question": "오늘 이루고 싶은 목표는 무엇이었나요?"
  },
  {
    "month": 6,
    "day": 19,
    "question": "오늘의 식사 중 가장 맛있었던 것은 무엇인가요?"
  },
  {
    "month": 6,
    "day": 20,
    "question": "오늘 내가 만난 사람 중 가장 인상 깊었던 사람은 누구인가요?"
  },
  {
    "month": 6,
    "day": 21,
    "question": "오늘의 하루를 노래 제목으로 표현한다면?"
  },
  {
    "month": 6,
    "day": 22,
    "question": "오늘 내가 해낸 일 중 가장 기뻤던 것은?"
  },
  {
    "month": 6,
    "day": 23,
    "question": "오늘 나에게 위로가 되었던 순간은?"
  },
  {
    "month": 6,
    "day": 24,
    "question": "오늘 발견한 작은 행복은 무엇인가요?"
  },
  {
    "month": 6,
    "day": 25,
    "question": "오늘 하루 중 가장 도전적인 순간은 무엇이었나요?"
  },
  {
    "month": 6,
    "day": 26,
    "question": "오늘 나의 일상에서 감사한 점은 무엇인가요?"
  },
  {
    "month": 6,
    "day": 27,
    "question": "오늘 내가 개선할 수 있는 점은 무엇인가요?"
  },
  {
    "month": 6,
    "day": 28,
    "question": "오늘 하루 중 가장 평화로웠던 순간은 언제였나요?"
  },
  {
    "month": 6,
    "day": 29,
    "question": "오늘 나를 행복하게 한 작은 일은 무엇인가요?"
  },
  {
    "month": 6,
    "day": 30,
    "question": "오늘 만약 되돌릴 수 있다면 무엇을 바꾸고 싶나요?"
  },
  {
    "month": 7,
    "day": 1,
    "question": "오늘 하루 가장 특별했던 순간은 무엇인가요?"
  },
  {
    "month": 7,
    "day": 2,
    "question": "오늘 나에게 가장 중요한 가치는 무엇이었나요?"
  },
  {
    "month": 7,
    "day": 3,
    "question": "최근에 나를 행복하게 만든 일은 무엇인가요?"
  },
  {
    "month": 7,
    "day": 4,
    "question": "오늘 하루를 한 문장으로 표현한다면?"
  },
  {
    "month": 7,
    "day": 5,
    "question": "지금 가장 감사한 것은 무엇인가요?"
  },
  {
    "month": 7,
    "day": 6,
    "question": "오늘 어떤 배움을 얻었나요?"
  },
  {
    "month": 7,
    "day": 7,
    "question": "오늘 나를 웃게 만든 일은 무엇인가요?"
  },
  {
    "month": 7,
    "day": 8,
    "question": "오늘 느낀 가장 강렬한 감정은 무엇인가요?"
  },
  {
    "month": 7,
    "day": 9,
    "question": "오늘 새롭게 시도한 일이 있다면 무엇인가요?"
  },
  {
    "month": 7,
    "day": 10,
    "question": "어린 시절 가장 좋아했던 일은 무엇인가요?"
  },
  {
    "month": 7,
    "day": 11,
    "question": "오늘 나를 자랑스럽게 만든 일은 무엇인가요?"
  },
  {
    "month": 7,
    "day": 12,
    "question": "오늘의 날씨와 나의 기분은 어땠나요?"
  },
  {
    "month": 7,
    "day": 13,
    "question": "오늘 내가 내린 가장 좋은 결정은 무엇인가요?"
  },
  {
    "month": 7,
    "day": 14,
    "question": "오늘 감사한 사람은 누구인가요?"
  },
  {
    "month": 7,
    "day": 15,
    "question": "오늘 내가 배운 가장 중요한 교훈은 무엇인가요?"
  },
  {
    "month": 7,
    "day": 16,
    "question": "오늘 하루를 점수로 매긴다면 몇 점인가요?"
  },
  {
    "month": 7,
    "day": 17,
    "question": "오늘 나의 기분을 색으로 표현한다면?"
  },
  {
    "month": 7,
    "day": 18,
    "question": "오늘 이루고 싶은 목표는 무엇이었나요?"
  },
  {
    "month": 7,
    "day": 19,
    "question": "오늘의 식사 중 가장 맛있었던 것은 무엇인가요?"
  },
  {
    "month": 7,
    "day": 20,
    "question": "오늘 내가 만난 사람 중 가장 인상 깊었던 사람은 누구인가요?"
  },
  {
    "month": 7,
    "day": 21,
    "question": "오늘의 하루를 노래 제목으로 표현한다면?"
  },
  {
    "month": 7,
    "day": 22,
    "question": "오늘 내가 해낸 일 중 가장 기뻤던 것은?"
  },
  {
    "month": 7,
    "day": 23,
    "question": "오늘 나에게 위로가 되었던 순간은?"
  },
  {
    "month": 7,
    "day": 24,
    "question": "오늘 발견한 작은 행복은 무엇인가요?"
  },
  {
    "month": 7,
    "day": 25,
    "question": "오늘 하루 중 가장 도전적인 순간은 무엇이었나요?"
  },
  {
    "month": 7,
    "day": 26,
    "question": "오늘 나의 일상에서 감사한 점은 무엇인가요?"
  },
  {
    "month": 7,
    "day": 27,
    "question": "오늘 내가 개선할 수 있는 점은 무엇인가요?"
  },
  {
    "month": 7,
    "day": 28,
    "question": "오늘 하루 중 가장 평화로웠던 순간은 언제였나요?"
  },
  {
    "month": 7,
    "day": 29,
    "question": "오늘 나를 행복하게 한 작은 일은 무엇인가요?"
  },
  {
    "month": 7,
    "day": 30,
    "question": "오늘 만약 되돌릴 수 있다면 무엇을 바꾸고 싶나요?"
  },
  {
    "month": 7,
    "day": 31,
    "question": "이번 달 가장 기억에 남는 일은 무엇인가요?"
  },
  {
    "month": 8,
    "day": 1,
    "question": "오늘 하루 가장 특별했던 순간은 무엇인가요?"
  },
  {
    "month": 8,
    "day": 2,
    "question": "오늘 나에게 가장 중요한 가치는 무엇이었나요?"
  },
  {
    "month": 8,
    "day": 3,
    "question": "최근에 나를 행복하게 만든 일은 무엇인가요?"
  },
  {
    "month": 8,
    "day": 4,
    "question": "오늘 하루를 한 문장으로 표현한다면?"
  },
  {
    "month": 8,
    "day": 5,
    "question": "지금 가장 감사한 것은 무엇인가요?"
  },
  {
    "month": 8,
    "day": 6,
    "question": "오늘 어떤 배움을 얻었나요?"
  },
  {
    "month": 8,
    "day": 7,
    "question": "오늘 나를 웃게 만든 일은 무엇인가요?"
  },
  {
    "month": 8,
    "day": 8,
    "question": "오늘 느낀 가장 강렬한 감정은 무엇인가요?"
  },
  {
    "month": 8,
    "day": 9,
    "question": "오늘 새롭게 시도한 일이 있다면 무엇인가요?"
  },
  {
    "month": 8,
    "day": 10,
    "question": "어린 시절 가장 좋아했던 일은 무엇인가요?"
  },
  {
    "month": 8,
    "day": 11,
    "question": "오늘 나를 자랑스럽게 만든 일은 무엇인가요?"
  },
  {
    "month": 8,
    "day": 12,
    "question": "오늘의 날씨와 나의 기분은 어땠나요?"
  },
  {
    "month": 8,
    "day": 13,
    "question": "오늘 내가 내린 가장 좋은 결정은 무엇인가요?"
  },
  {
    "month": 8,
    "day": 14,
    "question": "오늘 감사한 사람은 누구인가요?"
  },
  {
    "month": 8,
    "day": 15,
    "question": "오늘 내가 배운 가장 중요한 교훈은 무엇인가요?"
  },
  {
    "month": 8,
    "day": 16,
    "question": "오늘 하루를 점수로 매긴다면 몇 점인가요?"
  },
  {
    "month": 8,
    "day": 17,
    "question": "오늘 나의 기분을 색으로 표현한다면?"
  },
  {
    "month": 8,
    "day": 18,
    "question": "오늘 이루고 싶은 목표는 무엇이었나요?"
  },
  {
    "month": 8,
    "day": 19,
    "question": "오늘의 식사 중 가장 맛있었던 것은 무엇인가요?"
  },
  {
    "month": 8,
    "day": 20,
    "question": "오늘 내가 만난 사람 중 가장 인상 깊었던 사람은 누구인가요?"
  },
  {
    "month": 8,
    "day": 21,
    "question": "오늘의 하루를 노래 제목으로 표현한다면?"
  },
  {
    "month": 8,
    "day": 22,
    "question": "오늘 내가 해낸 일 중 가장 기뻤던 것은?"
  },
  {
    "month": 8,
    "day": 23,
    "question": "오늘 나에게 위로가 되었던 순간은?"
  },
  {
    "month": 8,
    "day": 24,
    "question": "오늘 발견한 작은 행복은 무엇인가요?"
  },
  {
    "month": 8,
    "day": 25,
    "question": "오늘 하루 중 가장 도전적인 순간은 무엇이었나요?"
  },
  {
    "month": 8,
    "day": 26,
    "question": "오늘 나의 일상에서 감사한 점은 무엇인가요?"
  },
  {
    "month": 8,
    "day": 27,
    "question": "오늘 내가 개선할 수 있는 점은 무엇인가요?"
  },
  {
    "month": 8,
    "day": 28,
    "question": "오늘 하루 중 가장 평화로웠던 순간은 언제였나요?"
  },
  {
    "month": 8,
    "day": 29,
    "question": "오늘 나를 행복하게 한 작은 일은 무엇인가요?"
  },
  {
    "month": 8,
    "day": 30,
    "question": "오늘 만약 되돌릴 수 있다면 무엇을 바꾸고 싶나요?"
  },
  {
    "month": 8,
    "day": 31,
    "question": "이번 달 가장 기억에 남는 일은 무엇인가요?"
  },
  {
    "month": 9,
    "day": 1,
    "question": "오늘 하루 가장 특별했던 순간은 무엇인가요?"
  },
  {
    "month": 9,
    "day": 2,
    "question": "오늘 나에게 가장 중요한 가치는 무엇이었나요?"
  },
  {
    "month": 9,
    "day": 3,
    "question": "최근에 나를 행복하게 만든 일은 무엇인가요?"
  },
  {
    "month": 9,
    "day": 4,
    "question": "오늘 하루를 한 문장으로 표현한다면?"
  },
  {
    "month": 9,
    "day": 5,
    "question": "지금 가장 감사한 것은 무엇인가요?"
  },
  {
    "month": 9,
    "day": 6,
    "question": "오늘 어떤 배움을 얻었나요?"
  },
  {
    "month": 9,
    "day": 7,
    "question": "오늘 나를 웃게 만든 일은 무엇인가요?"
  },
  {
    "month": 9,
    "day": 8,
    "question": "오늘 느낀 가장 강렬한 감정은 무엇인가요?"
  },
  {
    "month": 9,
    "day": 9,
    "question": "오늘 새롭게 시도한 일이 있다면 무엇인가요?"
  },
  {
    "month": 9,
    "day": 10,
    "question": "어린 시절 가장 좋아했던 일은 무엇인가요?"
  },
  {
    "month": 9,
    "day": 11,
    "question": "오늘 나를 자랑스럽게 만든 일은 무엇인가요?"
  },
  {
    "month": 9,
    "day": 12,
    "question": "오늘의 날씨와 나의 기분은 어땠나요?"
  },
  {
    "month": 9,
    "day": 13,
    "question": "오늘 내가 내린 가장 좋은 결정은 무엇인가요?"
  },
  {
    "month": 9,
    "day": 14,
    "question": "오늘 감사한 사람은 누구인가요?"
  },
  {
    "month": 9,
    "day": 15,
    "question": "오늘 내가 배운 가장 중요한 교훈은 무엇인가요?"
  },
  {
    "month": 9,
    "day": 16,
    "question": "오늘 하루를 점수로 매긴다면 몇 점인가요?"
  },
  {
    "month": 9,
    "day": 17,
    "question": "오늘 나의 기분을 색으로 표현한다면?"
  },
  {
    "month": 9,
    "day": 18,
    "question": "오늘 이루고 싶은 목표는 무엇이었나요?"
  },
  {
    "month": 9,
    "day": 19,
    "question": "오늘의 식사 중 가장 맛있었던 것은 무엇인가요?"
  },
  {
    "month": 9,
    "day": 20,
    "question": "오늘 내가 만난 사람 중 가장 인상 깊었던 사람은 누구인가요?"
  },
  {
    "month": 9,
    "day": 21,
    "question": "오늘의 하루를 노래 제목으로 표현한다면?"
  },
  {
    "month": 9,
    "day": 22,
    "question": "오늘 내가 해낸 일 중 가장 기뻤던 것은?"
  },
  {
    "month": 9,
    "day": 23,
    "question": "오늘 나에게 위로가 되었던 순간은?"
  },
  {
    "month": 9,
    "day": 24,
    "question": "오늘 발견한 작은 행복은 무엇인가요?"
  },
  {
    "month": 9,
    "day": 25,
    "question": "오늘 하루 중 가장 도전적인 순간은 무엇이었나요?"
  },
  {
    "month": 9,
    "day": 26,
    "question": "오늘 나의 일상에서 감사한 점은 무엇인가요?"
  },
  {
    "month": 9,
    "day": 27,
    "question": "오늘 내가 개선할 수 있는 점은 무엇인가요?"
  },
  {
    "month": 9,
    "day": 28,
    "question": "오늘 하루 중 가장 평화로웠던 순간은 언제였나요?"
  },
  {
    "month": 9,
    "day": 29,
    "question": "오늘 나를 행복하게 한 작은 일은 무엇인가요?"
  },
  {
    "month": 9,
    "day": 30,
    "question": "오늘 만약 되돌릴 수 있다면 무엇을 바꾸고 싶나요?"
  },
  {
    "month": 10,
    "day": 1,
    "question": "오늘 하루 가장 특별했던 순간은 무엇인가요?"
  },
  {
    "month": 10,
    "day": 2,
    "question": "오늘 나에게 가장 중요한 가치는 무엇이었나요?"
  },
  {
    "month": 10,
    "day": 3,
    "question": "최근에 나를 행복하게 만든 일은 무엇인가요?"
  },
  {
    "month": 10,
    "day": 4,
    "question": "오늘 하루를 한 문장으로 표현한다면?"
  },
  {
    "month": 10,
    "day": 5,
    "question": "지금 가장 감사한 것은 무엇인가요?"
  },
  {
    "month": 10,
    "day": 6,
    "question": "오늘 어떤 배움을 얻었나요?"
  },
  {
    "month": 10,
    "day": 7,
    "question": "오늘 나를 웃게 만든 일은 무엇인가요?"
  },
  {
    "month": 10,
    "day": 8,
    "question": "오늘 느낀 가장 강렬한 감정은 무엇인가요?"
  },
  {
    "month": 10,
    "day": 9,
    "question": "오늘 새롭게 시도한 일이 있다면 무엇인가요?"
  },
  {
    "month": 10,
    "day": 10,
    "question": "어린 시절 가장 좋아했던 일은 무엇인가요?"
  },
  {
    "month": 10,
    "day": 11,
    "question": "오늘 나를 자랑스럽게 만든 일은 무엇인가요?"
  },
  {
    "month": 10,
    "day": 12,
    "question": "오늘의 날씨와 나의 기분은 어땠나요?"
  },
  {
    "month": 10,
    "day": 13,
    "question": "오늘 내가 내린 가장 좋은 결정은 무엇인가요?"
  },
  {
    "month": 10,
    "day": 14,
    "question": "오늘 감사한 사람은 누구인가요?"
  },
  {
    "month": 10,
    "day": 15,
    "question": "오늘 내가 배운 가장 중요한 교훈은 무엇인가요?"
  },
  {
    "month": 10,
    "day": 16,
    "question": "오늘 하루를 점수로 매긴다면 몇 점인가요?"
  },
  {
    "month": 10,
    "day": 17,
    "question": "오늘 나의 기분을 색으로 표현한다면?"
  },
  {
    "month": 10,
    "day": 18,
    "question": "오늘 이루고 싶은 목표는 무엇이었나요?"
  },
  {
    "month": 10,
    "day": 19,
    "question": "오늘의 식사 중 가장 맛있었던 것은 무엇인가요?"
  },
  {
    "month": 10,
    "day": 20,
    "question": "오늘 내가 만난 사람 중 가장 인상 깊었던 사람은 누구인가요?"
  },
  {
    "month": 10,
    "day": 21,
    "question": "오늘의 하루를 노래 제목으로 표현한다면?"
  },
  {
    "month": 10,
    "day": 22,
    "question": "오늘 내가 해낸 일 중 가장 기뻤던 것은?"
  },
  {
    "month": 10,
    "day": 23,
    "question": "오늘 나에게 위로가 되었던 순간은?"
  },
  {
    "month": 10,
    "day": 24,
    "question": "오늘 발견한 작은 행복은 무엇인가요?"
  },
  {
    "month": 10,
    "day": 25,
    "question": "오늘 하루 중 가장 도전적인 순간은 무엇이었나요?"
  },
  {
    "month": 10,
    "day": 26,
    "question": "오늘 나의 일상에서 감사한 점은 무엇인가요?"
  },
  {
    "month": 10,
    "day": 27,
    "question": "오늘 내가 개선할 수 있는 점은 무엇인가요?"
  },
  {
    "month": 10,
    "day": 28,
    "question": "오늘 하루 중 가장 평화로웠던 순간은 언제였나요?"
  },
  {
    "month": 10,
    "day": 29,
    "question": "오늘 나를 행복하게 한 작은 일은 무엇인가요?"
  },
  {
    "month": 10,
    "day": 30,
    "question": "오늘 만약 되돌릴 수 있다면 무엇을 바꾸고 싶나요?"
  },
  {
    "month": 10,
    "day": 31,
    "question": "이번 달 가장 기억에 남는 일은 무엇인가요?"
  },
  {
    "month": 11,
    "day": 1,
    "question": "오늘 하루 가장 특별했던 순간은 무엇인가요?"
  },
  {
    "month": 11,
    "day": 2,
    "question": "오늘 나에게 가장 중요한 가치는 무엇이었나요?"
  },
  {
    "month": 11,
    "day": 3,
    "question": "최근에 나를 행복하게 만든 일은 무엇인가요?"
  },
  {
    "month": 11,
    "day": 4,
    "question": "오늘 하루를 한 문장으로 표현한다면?"
  },
  {
    "month": 11,
    "day": 5,
    "question": "지금 가장 감사한 것은 무엇인가요?"
  },
  {
    "month": 11,
    "day": 6,
    "question": "오늘 어떤 배움을 얻었나요?"
  },
  {
    "month": 11,
    "day": 7,
    "question": "오늘 나를 웃게 만든 일은 무엇인가요?"
  },
  {
    "month": 11,
    "day": 8,
    "question": "오늘 느낀 가장 강렬한 감정은 무엇인가요?"
  },
  {
    "month": 11,
    "day": 9,
    "question": "오늘 새롭게 시도한 일이 있다면 무엇인가요?"
  },
  {
    "month": 11,
    "day": 10,
    "question": "어린 시절 가장 좋아했던 일은 무엇인가요?"
  },
  {
    "month": 11,
    "day": 11,
    "question": "오늘 나를 자랑스럽게 만든 일은 무엇인가요?"
  },
  {
    "month": 11,
    "day": 12,
    "question": "오늘의 날씨와 나의 기분은 어땠나요?"
  },
  {
    "month": 11,
    "day": 13,
    "question": "오늘 내가 내린 가장 좋은 결정은 무엇인가요?"
  },
  {
    "month": 11,
    "day": 14,
    "question": "오늘 감사한 사람은 누구인가요?"
  },
  {
    "month": 11,
    "day": 15,
    "question": "오늘 내가 배운 가장 중요한 교훈은 무엇인가요?"
  },
  {
    "month": 11,
    "day": 16,
    "question": "오늘 하루를 점수로 매긴다면 몇 점인가요?"
  },
  {
    "month": 11,
    "day": 17,
    "question": "오늘 나의 기분을 색으로 표현한다면?"
  },
  {
    "month": 11,
    "day": 18,
    "question": "오늘 이루고 싶은 목표는 무엇이었나요?"
  },
  {
    "month": 11,
    "day": 19,
    "question": "오늘의 식사 중 가장 맛있었던 것은 무엇인가요?"
  },
  {
    "month": 11,
    "day": 20,
    "question": "오늘 내가 만난 사람 중 가장 인상 깊었던 사람은 누구인가요?"
  },
  {
    "month": 11,
    "day": 21,
    "question": "오늘의 하루를 노래 제목으로 표현한다면?"
  },
  {
    "month": 11,
    "day": 22,
    "question": "오늘 내가 해낸 일 중 가장 기뻤던 것은?"
  },
  {
    "month": 11,
    "day": 23,
    "question": "오늘 나에게 위로가 되었던 순간은?"
  },
  {
    "month": 11,
    "day": 24,
    "question": "오늘 발견한 작은 행복은 무엇인가요?"
  },
  {
    "month": 11,
    "day": 25,
    "question": "오늘 하루 중 가장 도전적인 순간은 무엇이었나요?"
  },
  {
    "month": 11,
    "day": 26,
    "question": "오늘 나의 일상에서 감사한 점은 무엇인가요?"
  },
  {
    "month": 11,
    "day": 27,
    "question": "오늘 내가 개선할 수 있는 점은 무엇인가요?"
  },
  {
    "month": 11,
    "day": 28,
    "question": "오늘 하루 중 가장 평화로웠던 순간은 언제였나요?"
  },
  {
    "month": 11,
    "day": 29,
    "question": "오늘 나를 행복하게 한 작은 일은 무엇인가요?"
  },
  {
    "month": 11,
    "day": 30,
    "question": "오늘 만약 되돌릴 수 있다면 무엇을 바꾸고 싶나요?"
  },
  {
    "month": 12,
    "day": 1,
    "question": "오늘 하루 가장 특별했던 순간은 무엇인가요?"
  },
  {
    "month": 12,
    "day": 2,
    "question": "오늘 나에게 가장 중요한 가치는 무엇이었나요?"
  },
  {
    "month": 12,
    "day": 3,
    "question": "최근에 나를 행복하게 만든 일은 무엇인가요?"
  },
  {
    "month": 12,
    "day": 4,
    "question": "오늘 하루를 한 문장으로 표현한다면?"
  },
  {
    "month": 12,
    "day": 5,
    "question": "지금 가장 감사한 것은 무엇인가요?"
  },
  {
    "month": 12,
    "day": 6,
    "question": "오늘 어떤 배움을 얻었나요?"
  },
  {
    "month": 12,
    "day": 7,
    "question": "오늘 나를 웃게 만든 일은 무엇인가요?"
  },
  {
    "month": 12,
    "day": 8,
    "question": "오늘 느낀 가장 강렬한 감정은 무엇인가요?"
  },
  {
    "month": 12,
    "day": 9,
    "question": "오늘 새롭게 시도한 일이 있다면 무엇인가요?"
  },
  {
    "month": 12,
    "day": 10,
    "question": "어린 시절 가장 좋아했던 일은 무엇인가요?"
  },
  {
    "month": 12,
    "day": 11,
    "question": "오늘 나를 자랑스럽게 만든 일은 무엇인가요?"
  },
  {
    "month": 12,
    "day": 12,
    "question": "오늘의 날씨와 나의 기분은 어땠나요?"
  },
  {
    "month": 12,
    "day": 13,
    "question": "오늘 내가 내린 가장 좋은 결정은 무엇인가요?"
  },
  {
    "month": 12,
    "day": 14,
    "question": "오늘 감사한 사람은 누구인가요?"
  },
  {
    "month": 12,
    "day": 15,
    "question": "오늘 내가 배운 가장 중요한 교훈은 무엇인가요?"
  },
  {
    "month": 12,
    "day": 16,
    "question": "오늘 하루를 점수로 매긴다면 몇 점인가요?"
  },
  {
    "month": 12,
    "day": 17,
    "question": "오늘 나의 기분을 색으로 표현한다면?"
  },
  {
    "month": 12,
    "day": 18,
    "question": "오늘 이루고 싶은 목표는 무엇이었나요?"
  },
  {
    "month": 12,
    "day": 19,
    "question": "오늘의 식사 중 가장 맛있었던 것은 무엇인가요?"
  },
  {
    "month": 12,
    "day": 20,
    "question": "오늘 내가 만난 사람 중 가장 인상 깊었던 사람은 누구인가요?"
  },
  {
    "month": 12,
    "day": 21,
    "question": "오늘의 하루를 노래 제목으로 표현한다면?"
  },
  {
    "month": 12,
    "day": 22,
    "question": "오늘 내가 해낸 일 중 가장 기뻤던 것은?"
  },
  {
    "month": 12,
    "day": 23,
    "question": "오늘 나에게 위로가 되었던 순간은?"
  },
  {
    "month": 12,
    "day": 24,
    "question": "오늘 발견한 작은 행복은 무엇인가요?"
  },
  {
    "month": 12,
    "day": 25,
    "question": "오늘 하루 중 가장 도전적인 순간은 무엇이었나요?"
  },
  {
    "month": 12,
    "day": 26,
    "question": "오늘 나의 일상에서 감사한 점은 무엇인가요?"
  },
  {
    "month": 12,
    "day": 27,
    "question": "오늘 내가 개선할 수 있는 점은 무엇인가요?"
  },
  {
    "month": 12,
    "day": 28,
    "question": "오늘 하루 중 가장 평화로웠던 순간은 언제였나요?"
  },
  {
    "month": 12,
    "day": 29,
    "question": "오늘 나를 행복하게 한 작은 일은 무엇인가요?"
  },
  {
    "month": 12,
    "day": 30,
    "question": "오늘 만약 되돌릴 수 있다면 무엇을 바꾸고 싶나요?"
  },
  {
    "month": 12,
    "day": 31,
    "question": "이번 달 가장 기억에 남는 일은 무엇인가요?"
  }
]
